[
  {
    "address": "0xc4c7ea4fab34bd9fb9a5e1b1a98df76e26e6407c",
    "tokenName": "CocosTokenV2",
    "tokenSymbol": "COCOS",
    "website": "https://www.cocosbcx.io"
  },
  {
    "address": "0x2162f572b25f7358db9376ab58a947a4e45cede1",
    "tokenName": "LABEL",
    "tokenSymbol": "LBL",
    "website": "https://label.foundation/"
  },
  {
    "address": "0xf9209d900f7ad1dc45376a2caa61c78f6dea53b6",
    "tokenName": "LIFT.Kitchen",
    "tokenSymbol": "LIFT",
    "website": "https://lift.kitchen/"
  },
  {
    "address": "0x1c7ede23b1361acc098a1e357c9085d131b34a01",
    "tokenName": "Shine",
    "tokenSymbol": "SHN",
    "website": "https://shinedao.finance/"
  },
  {
    "address": "0x48e77357db13bc80ed175bd20a6302b1bb66bbd3",
    "tokenName": "Nomavo",
    "tokenSymbol": "Noma",
    "website": "https://nomavotoken.com/"
  },
  {
    "address": "0xa31fdbaa772745d11843efeda9922dcbf5460672",
    "tokenName": "Lift.Kitchen...",
    "tokenSymbol": "CTRL",
    "website": "https://lift.kitchen/"
  },
  {
    "address": "0xddd2Ec6bD01506A8510aBa02393fB058D9F6CE89",
    "tokenName": "Valhalla",
    "tokenSymbol": "VAL",
    "website": "https://valdao.org/"
  },
  {
    "address": "0x1EddEe3Fa21591a9637f88DaB9615C33Ee636b9D",
    "tokenName": "WeToken",
    "tokenSymbol": "WON",
    "website": "https://www.weblock.vip/"
  },
  {
    "address": "0x660e71483785f66133548B10f6926dC332b06e61",
    "tokenName": "Adelphoi",
    "tokenSymbol": "ADL",
    "website": "https://www.adelphoi.io/"
  },
  {
    "address": "0xafce9b78d409bf74980cacf610afb851bf02f257",
    "tokenName": "Lift.Kitchen...",
    "tokenSymbol": "LFBTC",
    "website": "https://lift.kitchen/"
  },
  {
    "address": "0xef51c9377feb29856e61625caf9390bd0b67ea18",
    "tokenName": "Bionic",
    "tokenSymbol": "BNC",
    "website": "https://bionic-coin.io/"
  },
  {
    "address": "0x9a03c4d95a8e31e1e11a4319066475cd12b22dee",
    "tokenName": "Bithemoth",
    "tokenSymbol": "BHM",
    "website": "https://bithemoth.com/"
  }
]
