[
  {
    "tokenName": "Meowshi",
    "tokenSymbol": "MEOW",
    "website": "https://sushi.com/",
    "address": "0x650f44ed6f1fe0e1417cb4b3115d52494b4d9b6d",
    "tokenImage": "https://etherscan.io/token/images/meowshi_32.png"
  },
  {
    "tokenName": "SushiToken",
    "tokenSymbol": "SUSHI",
    "website": "https://sushi.com/",
    "address": "0x6b3595068778dd592e39a122f4f5a5cf09c90fe2",
    "tokenImage": "https://etherscan.io/token/images/sushitoken_32.png"
  },
  {
    "tokenName": "SushiBar",
    "tokenSymbol": "xSUSHI",
    "website": "https://sushiswap.org/",
    "address": "0x8798249c2e607446efb7ad49ec89dd1865ff4272",
    "tokenImage": "https://etherscan.io/token/images/sushibar_32.png"
  }
]
