[
  {
    "address": "0x041faf9cc764333a2cd172bc32cbd3ca36b02bfe",
    "tokenName": "Slash Financ...",
    "tokenSymbol": "SLSH",
    "website": "https://slash.financial/"
  },
  {
    "address": "0x43501ad052e817962e406f913bffaaafce48574d",
    "tokenName": "The Crypto S...",
    "tokenSymbol": "TCS",
    "website": "https://thecryptostar.co/"
  },
  {
    "address": "0x50cfb4d1693d9a638e3db1cc530aafc98f2afbaf",
    "tokenName": "UFBI",
    "tokenSymbol": "UFBI",
    "website": "https://ufbi.org/ufbicoin"
  },
  {
    "address": "0x5ae89b52f6b5d25eba50f0441f91a81968689d95",
    "tokenName": "A-NATION",
    "tokenSymbol": "ANATIO...",
    "website": "https://anation.media/"
  },
  {
    "address": "0x737526fe915396fa3d10be87789bd3c16e88e454",
    "tokenName": "E21",
    "tokenSymbol": "E21",
    "website": "https://www.e21coin.com"
  },
  {
    "address": "0xe594e6858cdf0a1072703577e9169f161b8f1b37",
    "tokenName": "CryptoPol Ne...",
    "tokenSymbol": "CPNEWS",
    "website": "https://www.cryptopol.news/"
  },
  {
    "address": "0xec4956111924e6d18099fa19802748e222a15000",
    "tokenName": "Crypto Media...",
    "tokenSymbol": "CMN",
    "website": "https://www.cmntoken.io/"
  },
  {
    "address": "0xeceb87cf00dcbf2d4e2880223743ff087a995ad9",
    "tokenName": "NUM Token [v...",
    "tokenSymbol": "NUM",
    "website": "https://www.numbersprotocol.io/"
  },
  {
    "address": "0xf31327c3c16b58d365efc82e66b7a38cd123cbf8",
    "tokenName": "1COIN",
    "tokenSymbol": "1COIN",
    "website": "https://1coin.ltd/"
  },
  {
    "address": "0xf323943a6825ef60631a0bba7efb7a80ec1ff870",
    "tokenName": "Alternative ...",
    "tokenSymbol": "AMKRYP...",
    "website": "https://amkrypto.com/"
  },
  {
    "address": "0xf72d030f6ca545357b361a0fd36c77da8837f9fb",
    "tokenName": "ALTO TOKEN",
    "tokenSymbol": "ALTO",
    "website": "https://altostream.app/"
  }
]
