[
  {
    "address": "0x0183c8ee8ce9e7a7a03a226da3dd78ff5073e7f0",
    "tokenName": "Helper Coin",
    "tokenSymbol": "HLPR",
    "website": "https://helperworld.io/"
  },
  {
    "address": "0x0197bccbdbafad1645280b14024fce0770af4e66",
    "tokenName": "BHUMI",
    "tokenSymbol": "BHUMI",
    "website": "https://www.bhumi.biz.id/"
  },
  {
    "address": "0x1a3c7d6cb66299f769040e6d4cf0c1945f6a2f32",
    "tokenName": "KIATOKEN",
    "tokenSymbol": "KIA",
    "website": "https://kiahelps.com/"
  },
  {
    "address": "0x42614e5acf9c084a8afdff402ecd89d19f675c00",
    "tokenName": "Orbital Stat...",
    "tokenSymbol": "OSEX",
    "website": "https://osexnetwork.com/"
  },
  {
    "address": "0x46d502fac9aea7c5bc7b13c8ec9d02378c33d36f",
    "tokenName": "WolfSafePoor...",
    "tokenSymbol": "WSPP",
    "website": "https://wolfsafepoorpeople.com/"
  },
  {
    "address": "0x6f06e6bed64cf4c4187c06ee2a4732f6a171bc4e",
    "tokenName": "FoodChain Gl...",
    "tokenSymbol": "FOOD",
    "website": "https://foodchain.global/"
  },
  {
    "address": "0x7dce33a5611f73ea80248d7a259b1a66e87ada48",
    "tokenName": "Humans Care ...",
    "tokenSymbol": "HCFC",
    "website": "https://carefound.io/"
  },
  {
    "address": "0x8449c099d8fbf892d6e6cb3ad29db5e4f4dce6e3",
    "tokenName": "PANCAT",
    "tokenSymbol": "PANCAT",
    "website": "https://pancatcoin.com/"
  },
  {
    "address": "0x999e2e604f48de45480f97b5037a70aa2a78b488",
    "tokenName": "Kindly Coin",
    "tokenSymbol": "KIND",
    "website": "https://kindlycoin.com/"
  },
  {
    "address": "0xa8ce085c3523f932facddf3187852d989627a8d1",
    "tokenName": "SuperFoodz",
    "tokenSymbol": "SF",
    "website": "http://www.superfoodz.io/"
  },
  {
    "address": "0xa9c04f23ee2298613285a102a41267922c6cc205",
    "tokenName": "Kingdom",
    "tokenSymbol": "KDM",
    "website": "https://kingdomtoken.org/"
  },
  {
    "address": "0xd373313edf82aef845c9b86b600e58fa149cb0f3",
    "tokenName": "CharityToken",
    "tokenSymbol": "CHAT",
    "website": "https://www.charitytoken.online/"
  },
  {
    "address": "0xd4cce747e623ce2d72322892e5db238e2a5eb4f3",
    "tokenName": "Humans Care ...",
    "tokenSymbol": "HCFW",
    "website": "https://carefound.io/hcf"
  },
  {
    "address": "0xe6f0523b9dd59ca6166ececc3ae7e7cedf77a731",
    "tokenName": "Pest Free To...",
    "tokenSymbol": "PFT",
    "website": "https://pestfreetoken.co.nz/"
  },
  {
    "address": "0xecca5f7add0ff33e417ff02114f7e3a648b2db71",
    "tokenName": "Creamon",
    "tokenSymbol": "CRM",
    "website": "https://allaughs.com/"
  },
  {
    "address": "0xf3f7754d1859809435c10c10bdad1d7036a01799",
    "tokenName": "SloughiINU",
    "tokenSymbol": "SLGi",
    "website": "https://www.sloughiinu.xyz/"
  }
]
