[
  {
    "tokenName": "Sola Token",
    "tokenSymbol": "SOL",
    "website": "https://sola.foundation/",
    "address": "0x1f54638b7737193ffd86c19ec51907a7c41755d8",
    "tokenImage": "https://etherscan.io/token/images/sola_28.png"
  },
  {
    "tokenName": "Lira Cash",
    "tokenSymbol": "LIRA",
    "website": "http://www.lira.cash/",
    "address": "0x49aaa160506f7e07e6c3f6cd6316b6866025cdcb",
    "tokenImage": "https://etherscan.io/token/images/liracash_28.png"
  },
  {
    "tokenName": "Onyx USD",
    "tokenSymbol": "OUSD",
    "website": "https://onyx.to/",
    "address": "0xd2d01dd6aa7a2f5228c7c17298905a7c7e1dfe81",
    "tokenImage": "https://etherscan.io/token/images/onyxusd_32.png?v=2"
  },
  {
    "tokenName": "Onyx S&P 500 Short",
    "tokenSymbol": "OSPVS",
    "website": "https://onyx.to/",
    "address": "0xf7d1f35518950e78c18e5a442097ca07962f4d8a",
    "tokenImage": "https://etherscan.io/token/images/onyxs&p500short_32.png?=2"
  },
  {
    "tokenName": "Onyx S&P 500",
    "tokenSymbol": "OSPV",
    "website": "https://onyx.to/",
    "address": "0xfcce9526e030f1691966d5a651f5ebe1a5b4c8e4",
    "tokenImage": "https://etherscan.io/token/images/onyxs&p500_32.png"
  }
]
