[
  {
    "address": "0x0994206dfe8de6ec6920ff4d779b0d950605fb53",
    "tokenName": "Curve DAO Token",
    "tokenSymbol": "CRV",
    "website": "https://curve.fi"
  },
  {
    "address": "0x1574564fcfd15bccb3fe04e9818f61131ea74066",
    "tokenName": "JARVIS",
    "tokenSymbol": "JARVIS",
    "website": "https://jarvis.network/"
  },
  {
    "address": "0x15e770b95edd73fd96b02ece0266247d50895e76",
    "tokenName": "Jarvis Reward Token",
    "tokenSymbol": "JRT",
    "website": "https://jarvis.network/"
  },
  {
    "address": "0x9a601c5bb360811d96a23689066af316a30c3027",
    "tokenName": "Pika",
    "tokenSymbol": "PIKA",
    "website": "https://pikaprotocol.com/"
  },
  {
    "address": "0x9f46a936be9114bd2f71965a87c003341448b47e",
    "tokenName": "JARVIS",
    "tokenSymbol": "JARVIS",
    "website": "https://jarvis.network/"
  },
  {
    "address": "0xe4d8701c69b3b94a620ff048e4226c895b67b2c0",
    "tokenName": "Minerva",
    "tokenSymbol": "MINE",
    "website": "https://www.minerva.money/"
  },
  {
    "address": "0xf1a0da3367bc7aa04f8d94ba57b862ff37ced174",
    "tokenName": "ShapeShift FOX",
    "tokenSymbol": "FOX",
    "website": "https://shapeshift.com/"
  }
]
